[
    {
        "ID": 4,
        "Name": "MMLGTM",
        "Type": 58,
        "Scale": 2.25,
        "Transform": [
            [
                -0.024541229009628297,
                0.99969881772995,
                -0.0,
                0.0
            ],
            [
                -0.99969881772995,
                -0.024541229009628297,
                0.0,
                0.0
            ],
            [
                0.0,
                0.0,
                1.0,
                0.0
            ],
            [
                2.5,
                0.0,
                -4.0,
                1.0
            ]
        ]
    }
]